tjwb/__init__.py
tjwb/columns_constant.py
tjwb/dataset.py
tjwb/tjwb.py
tjwb-3.1.0.dist-info/LICENSE
tjwb-3.1.0.dist-info/METADATA
tjwb-3.1.0.dist-info/WHEEL
tjwb-3.1.0.dist-info/RECORD
