Metadata-Version: 2.1
Name: tjwb
Version: 3.1.0
Summary: Python library for reservoir water balance calculations.
Home-page: https://github.com/duynguyen02/tjwb
Author: Duy Nguyen
Author-email: duynguyen02.dev@gmail.com
Requires-Python: >=3.9,<4.0
Classifier: Programming Language :: Python :: 3
Classifier: Programming Language :: Python :: 3.9
Classifier: Programming Language :: Python :: 3.10
Classifier: Programming Language :: Python :: 3.11
Classifier: Programming Language :: Python :: 3.12
Classifier: Programming Language :: Python :: 3.13
Requires-Dist: pandas (>=2.2.3,<3.0.0)
Project-URL: Repository, https://github.com/duynguyen02/tjwb
